DLATCH.v

// D-latch module(circuit) 
//
module DLATCH(Q, En, D);
	output Q, Qbar; //  Q, or Q_bar
	input En, D;
	
	wire andout_1, andout_2;  

	and AND_1(andout_1, En, ~D);		
	and AND_2(andout_2, En, D);
	
	nor NOR_1(Q, andout_1, Qbar );
	nor NOR_2(Qbar, andout_2, Q);	

endmodule //DLATCH

DLATCH_tb.v
//
// Test bench for DLATCH module
//

module DLATCH_tb;
	reg D, En;
	wire Q_value, Qbar_value;
	
	DLATCH dut( .D(D), .En(En),
		    .Q(Q_value));

initial 
	begin
	D = 0; En = 0;
/*	#5 En = 0;  D = 1;
	#5 En = 1;  D = 0;
	#5 En = 0;  D = 1;
	#5 En = 1;  D = 0;
	#5 En = 0;  D = 1;
	#5 En = 1;  D = 0;
	#5 En = 0;  D = 1;
*/
	#3 D = 1; 
	#5 D = 0; 
	#3 D = 1; 
	#20 D = 0;
	#5 D = 1;
	#3 D = 0;
	#2 D = 1;
	#20 D = 0; 	
	
	#10 $finish;
end //initial

//Enable generator
always begin
	#5 En = ~En; 
end

initial 
	begin
	$monitor("simtime = %g, D = %b,En = %b, Q_value = %b",$time, D,En, Q_value);
end //initial

initial 
begin
	$display("\007"); //ring a bell)
	$dumpfile("DLATCH.vcd");
	$dumpvars(0, dut);
end


endmodule

DLATCH.vcd
$date
	Thu Sep  3 16:32:41 2020
$end
$version
	Icarus Verilog
$end
$timescale
	1s
$end
$scope module DLATCH_tb $end
$scope module dut $end
$var wire 1 ! D $end
$var wire 1 " En $end
$var wire 1 # Q $end
$var wire 1 $ Qbar $end
$var wire 1 % andout_1 $end
$var wire 1 & andout_2 $end
$upscope $end
$upscope $end
$enddefinitions $end
#0
$dumpvars
0&
0%
x$
x#
0"
0!
$end
#3
1!
#5
1#
0$
1&
1"
#8
1$
0#
1%
0&
0!
#10
0%
0"
#11
1!
#15
1#
0$
1&
1"
#20
0&
0"
#25
1&
1"
#30
0&
0"
#31
0!
#35
1$
0#
1%
1"
#36
1#
0%
0$
1&
1!
#39
1$
0#
1%
0&
0!
#40
0%
0"
#41
1!
#45
1#
0$
1&
1"
#50
0&
0"
#55
1&
1"
#60
0&
0"
#61
0!
#65
1$
0#
1%
1"
#70
0%
0"
